{
"meta":{"test_sets":[],"test_metrics":[],"learn_metrics":[{"best_value":"Min","name":"MultiClass"}],"launch_mode":"Train","parameters":"","iteration_count":100,"learn_sets":["learn"],"name":"experiment"},
"iterations":[
{"learn":[4.246736912],"iteration":0,"passed_time":10.45770313,"remaining_time":1035.31261},
{"learn":[4.032523232],"iteration":1,"passed_time":12.96954982,"remaining_time":635.5079413},
{"learn":[3.907180388],"iteration":2,"passed_time":31.28243246,"remaining_time":1011.465316},
{"learn":[3.807472948],"iteration":3,"passed_time":40.67517353,"remaining_time":976.2041648},
{"learn":[3.668097955],"iteration":4,"passed_time":56.78696627,"remaining_time":1078.952359},
{"learn":[3.578375009],"iteration":5,"passed_time":60.45110034,"remaining_time":947.0672387},
{"learn":[3.508057966],"iteration":6,"passed_time":75.71375291,"remaining_time":1005.911289},
{"learn":[3.442888436],"iteration":7,"passed_time":88.25749461,"remaining_time":1014.961188},
{"learn":[3.396045108],"iteration":8,"passed_time":103.7078463,"remaining_time":1048.601557},
{"learn":[3.347584417],"iteration":9,"passed_time":111.5865357,"remaining_time":1004.278821},
{"learn":[3.312655721],"iteration":10,"passed_time":128.5716645,"remaining_time":1040.261649},
{"learn":[3.280670823],"iteration":11,"passed_time":145.0389509,"remaining_time":1063.618973},
{"learn":[3.247739811],"iteration":12,"passed_time":160.2193873,"remaining_time":1072.237438},
{"learn":[3.218856706],"iteration":13,"passed_time":175.6381473,"remaining_time":1078.920048},
{"learn":[3.192616988],"iteration":14,"passed_time":184.3181607,"remaining_time":1044.469578},
{"learn":[3.172578602],"iteration":15,"passed_time":186.9812077,"remaining_time":981.6513405},
{"learn":[3.147830093],"iteration":16,"passed_time":204.2163503,"remaining_time":997.0562985},
{"learn":[3.125356974],"iteration":17,"passed_time":221.0990655,"remaining_time":1007.229076},
{"learn":[3.106533371],"iteration":18,"passed_time":237.3342821,"remaining_time":1011.793519},
{"learn":[3.088204693],"iteration":19,"passed_time":253.1569201,"remaining_time":1012.627681},
{"learn":[3.072431267],"iteration":20,"passed_time":271.6382065,"remaining_time":1021.877063},
{"learn":[3.055301768],"iteration":21,"passed_time":287.278709,"remaining_time":1018.533605},
{"learn":[3.037560002],"iteration":22,"passed_time":302.3353385,"remaining_time":1012.166133},
{"learn":[3.027330298],"iteration":23,"passed_time":304.9680993,"remaining_time":965.7323145},
{"learn":[3.012348692],"iteration":24,"passed_time":320.9650541,"remaining_time":962.8951624},
{"learn":[2.994885674],"iteration":25,"passed_time":337.3512855,"remaining_time":960.1536586},
{"learn":[2.98114409],"iteration":26,"passed_time":353.7359564,"remaining_time":956.3972154},
{"learn":[2.972967208],"iteration":27,"passed_time":360.3027706,"remaining_time":926.4928387},
{"learn":[2.958985584],"iteration":28,"passed_time":376.3172431,"remaining_time":921.3284228},
{"learn":[2.945964936],"iteration":29,"passed_time":392.3606585,"remaining_time":915.5082033},
{"learn":[2.933014574],"iteration":30,"passed_time":408.1526208,"remaining_time":908.4687365},
{"learn":[2.926858293],"iteration":31,"passed_time":412.4768416,"remaining_time":876.5132885},
{"learn":[2.917981422],"iteration":32,"passed_time":431.2592473,"remaining_time":875.5869567},
{"learn":[2.911607139],"iteration":33,"passed_time":449.4565466,"remaining_time":872.4744728},
{"learn":[2.903463836],"iteration":34,"passed_time":467.9348746,"remaining_time":869.0219101},
{"learn":[2.895637468],"iteration":35,"passed_time":486.4029664,"remaining_time":864.7163846},
{"learn":[2.884150526],"iteration":36,"passed_time":503.5513445,"remaining_time":857.3982353},
{"learn":[2.874192979],"iteration":37,"passed_time":519.4682711,"remaining_time":847.5534949},
{"learn":[2.866333605],"iteration":38,"passed_time":536.3181273,"remaining_time":838.856558},
{"learn":[2.856141802],"iteration":39,"passed_time":551.8497255,"remaining_time":827.7745882},
{"learn":[2.848450917],"iteration":40,"passed_time":568.916371,"remaining_time":818.6845339},
{"learn":[2.841347738],"iteration":41,"passed_time":585.304938,"remaining_time":808.2782478},
{"learn":[2.832230776],"iteration":42,"passed_time":601.2013976,"remaining_time":796.9413875},
{"learn":[2.823557532],"iteration":43,"passed_time":619.6265485,"remaining_time":788.6156071},
{"learn":[2.816938961],"iteration":44,"passed_time":637.7167253,"remaining_time":779.4315532},
{"learn":[2.814559452],"iteration":45,"passed_time":640.452961,"remaining_time":751.8360847},
{"learn":[2.809699439],"iteration":46,"passed_time":658.8238067,"remaining_time":742.9289735},
{"learn":[2.799789686],"iteration":47,"passed_time":674.4629822,"remaining_time":730.6682307},
{"learn":[2.792259746],"iteration":48,"passed_time":692.7710244,"remaining_time":721.0473927},
{"learn":[2.781378702],"iteration":49,"passed_time":707.8737574,"remaining_time":707.8737574},
{"learn":[2.770626015],"iteration":50,"passed_time":723.8573939,"remaining_time":695.4708294},
{"learn":[2.764937629],"iteration":51,"passed_time":742.055836,"remaining_time":684.9746179},
{"learn":[2.759444553],"iteration":52,"passed_time":760.3739387,"remaining_time":674.2938702},
{"learn":[2.753278493],"iteration":53,"passed_time":778.8010741,"remaining_time":663.4231372},
{"learn":[2.740530034],"iteration":54,"passed_time":795.047778,"remaining_time":650.4936365},
{"learn":[2.731459338],"iteration":55,"passed_time":810.3196922,"remaining_time":636.6797581},
{"learn":[2.721648684],"iteration":56,"passed_time":825.7070737,"remaining_time":622.9018276},
{"learn":[2.7067466],"iteration":57,"passed_time":841.0072485,"remaining_time":609.0052489},
{"learn":[2.698661499],"iteration":58,"passed_time":857.8078244,"remaining_time":596.1037424},
{"learn":[2.693020552],"iteration":59,"passed_time":874.5739398,"remaining_time":583.0492932},
{"learn":[2.685964394],"iteration":60,"passed_time":890.695778,"remaining_time":569.4612351},
{"learn":[2.679258841],"iteration":61,"passed_time":903.3521454,"remaining_time":553.6674439},
{"learn":[2.670845127],"iteration":62,"passed_time":919.972958,"remaining_time":540.3015785},
{"learn":[2.660924501],"iteration":63,"passed_time":935.1605152,"remaining_time":526.0277898},
{"learn":[2.648881892],"iteration":64,"passed_time":951.7316123,"remaining_time":512.4708681},
{"learn":[2.644748955],"iteration":65,"passed_time":969.1946172,"remaining_time":499.2820756},
{"learn":[2.636075958],"iteration":66,"passed_time":984.3021069,"remaining_time":484.8055154},
{"learn":[2.633002907],"iteration":67,"passed_time":1002.242017,"remaining_time":471.6433019},
{"learn":[2.6248016],"iteration":68,"passed_time":1018.426092,"remaining_time":457.5537516},
{"learn":[2.616800582],"iteration":69,"passed_time":1034.73218,"remaining_time":443.4566484},
{"learn":[2.613182395],"iteration":70,"passed_time":1052.305473,"remaining_time":429.8149114},
{"learn":[2.606436862],"iteration":71,"passed_time":1068.318643,"remaining_time":415.4572502},
{"learn":[2.600872969],"iteration":72,"passed_time":1083.773068,"remaining_time":400.8475732},
{"learn":[2.595833264],"iteration":73,"passed_time":1101.092032,"remaining_time":386.8701736},
{"learn":[2.586191434],"iteration":74,"passed_time":1116.927637,"remaining_time":372.3092124},
{"learn":[2.581652919],"iteration":75,"passed_time":1134.274532,"remaining_time":358.1919576},
{"learn":[2.57355271],"iteration":76,"passed_time":1150.529185,"remaining_time":343.6645619},
{"learn":[2.566015284],"iteration":77,"passed_time":1166.212506,"remaining_time":328.9317325},
{"learn":[2.556631238],"iteration":78,"passed_time":1181.497319,"remaining_time":314.0689077},
{"learn":[2.552376195],"iteration":79,"passed_time":1198.434937,"remaining_time":299.6087342},
{"learn":[2.543278288],"iteration":80,"passed_time":1213.412726,"remaining_time":284.6276765},
{"learn":[2.537142236],"iteration":81,"passed_time":1230.430319,"remaining_time":270.0944602},
{"learn":[2.522263527],"iteration":82,"passed_time":1246.385981,"remaining_time":255.2838755},
{"learn":[2.514135226],"iteration":83,"passed_time":1261.377745,"remaining_time":240.2624276},
{"learn":[2.510462322],"iteration":84,"passed_time":1278.722701,"remaining_time":225.6569472},
{"learn":[2.5039962],"iteration":85,"passed_time":1294.7963,"remaining_time":210.780793},
{"learn":[2.495292921],"iteration":86,"passed_time":1309.943593,"remaining_time":195.7386978},
{"learn":[2.487443462],"iteration":87,"passed_time":1326.102954,"remaining_time":180.8322211},
{"learn":[2.479445802],"iteration":88,"passed_time":1342.202696,"remaining_time":165.8902209},
{"learn":[2.472261856],"iteration":89,"passed_time":1358.841892,"remaining_time":150.9824324},
{"learn":[2.46676012],"iteration":90,"passed_time":1375.86599,"remaining_time":136.0746584},
{"learn":[2.462384254],"iteration":91,"passed_time":1392.925009,"remaining_time":121.1239138},
{"learn":[2.450406585],"iteration":92,"passed_time":1408.38893,"remaining_time":106.0077689},
{"learn":[2.443741666],"iteration":93,"passed_time":1424.264416,"remaining_time":90.91049466},
{"learn":[2.439319869],"iteration":94,"passed_time":1441.705737,"remaining_time":75.8792493},
{"learn":[2.431555283],"iteration":95,"passed_time":1458.063445,"remaining_time":60.75264356},
{"learn":[2.418847],"iteration":96,"passed_time":1471.945186,"remaining_time":45.52407792},
{"learn":[2.414544306],"iteration":97,"passed_time":1489.307644,"remaining_time":30.39403354},
{"learn":[2.398705092],"iteration":98,"passed_time":1503.287722,"remaining_time":15.18472447},
{"learn":[2.385504471],"iteration":99,"passed_time":1517.383103,"remaining_time":0}
]}